{
 "id": 428,
 "slug": "comment-connaitre-son-numero-de-telephone-fixe",
 "title": "Comment connaitre son numero de telephone fixe",
 "date": "2022-09-05T17:57:06",
 "modified": "2023-12-27T12:18:10",
 "excerpt": "Si vous avez un téléphone fixe, il existe plusieurs façons de trouver votre numéro. La plus évidente est de vous appeler d&rsquo;un autre téléphone, mais vous pouvez aussi vérifier l&rsquo;identité de l&rsquo;appelant ou chercher votre numéro dans les pages blanches. Si vous avez une ligne numérique",
 "image": "/media/428.webp",
 "imageAlt": "Comment connaitre son numero de telephone fixe",
 "category": "infos",
 "tags": [],
 "html": "<p>Si vous avez un téléphone fixe, il existe plusieurs façons de trouver votre numéro. La plus évidente est de vous appeler d&rsquo;un autre téléphone, mais vous pouvez aussi vérifier l&rsquo;identité de l&rsquo;appelant ou chercher votre numéro dans les pages blanches. Si vous avez une ligne numérique, vous pouvez même obtenir votre numéro en ligne. Dans cet article, nous allons explorer toutes ces méthodes et bien d&rsquo;autres pour vous aider à trouver comment obtenir votre propre numéro de téléphone fixe si le vôtre n&rsquo;est pas inscrit sur une vieille facture quelque part.</p>\n<h2>Appelez vous-même d&rsquo;un autre téléphone</h2>\n<p>Vous pouvez vous appeler depuis un autre téléphone. Composez le numéro, et vous entendrez une sonnerie. Il s&rsquo;agit de votre numéro de ligne fixe. Si vous n&rsquo;entendez pas de sonnerie, cela signifie que vous n&rsquo;avez pas de ligne fixe.</p>\n<h2>Vérifiez votre identification d&rsquo;appelant si vous l&rsquo;avez</h2>\n<p>Si vous avez le service d&rsquo;identification de l&rsquo;appelant, il affichera le numéro de la personne qui appelle. Si vous ne disposez pas de ce service et que vous essayez de trouver votre numéro de téléphone fixe, appelez votre compagnie de téléphone. Le représentant du service à la clientèle pourra peut-être vous aider à déterminer votre numéro de téléphone s&rsquo;il a accès à cette information dans sa base de données.</p>\n<p>Si le service d&rsquo;identification de l&rsquo;appelant est disponible sur votre ligne, vérifiez auprès de la compagnie de téléphone depuis combien de temps il est activé et si des changements ont été apportés récemment (comme le passage d&rsquo;une ligne téléphonique ordinaire à une ligne numérique).</p>\n<h2>Cherchez votre numéro dans les pages blanches</h2>\n<p>Si vous avez un téléphone fixe, votre numéro se trouve très probablement dans les pages blanches. Les pages blanches sont un répertoire des noms, adresses et numéros de téléphone des personnes. Pour trouver votre numéro dans les pages blanches</p>\n<ul>\n<li>Cherchez « annuaire téléphonique » à l&rsquo;aide d&rsquo;un moteur de recherche en ligne comme Google ou Bing. Vous pouvez utiliser des mots clés tels que « annuaire téléphonique » ou « pages blanches ».</li>\n<li>Sélectionnez une entreprise ou une personne qui vend ou publie des annuaires téléphoniques dans votre région. Il peut s&rsquo;agir d&rsquo;entreprises spécialisées dans la vente d&rsquo;annuaires (comme Dex Media), de journaux et d&rsquo;autres publications imprimées qui vendent des annuaires dans le cadre de leur gamme de produits (par exemple, The New York Times Company), de bibliothèques qui distribuent gratuitement au public des listes de téléphones par l&rsquo;intermédiaire des bureaux des administrations locales, etc.</li>\n</ul>\n<p>Maintenant que vous savez comment trouver votre numéro de téléphone fixe !</p>\n<h2>Obtenez votre numéro en ligne si vous avez une ligne numérique</h2>\n<p>Si vous avez une ligne numérique (c&rsquo;est-à-dire une ligne terrestre), le moyen le plus simple de trouver votre numéro est d&rsquo;utiliser un moteur de recherche tel que Google, Yahoo !, Ask ou Bing. Allez sur le site web et entrez votre numéro de téléphone dans le champ de recherche. Cliquez sur le premier lien qui apparaît et attendez qu&rsquo;il se charge. Une fois qu&rsquo;il est chargé, cherchez votre numéro de téléphone sur cette page.</p>\n<h2>Appelez votre fournisseur de services téléphoniques</h2>\n<p>Interlocuteur : Bonjour, je m&rsquo;appelle Susan. J&rsquo;appelle du fournisseur de services téléphoniques afin de vérifier le statut de mon numéro de téléphone.</p>\n<p>Appelant : Bonjour ! Je m&rsquo;appelle Susan et j&rsquo;appelle du bureau de notre société afin de me renseigner sur votre numéro de téléphone fixe.</p>\n<p>Je veux m&rsquo;assurer que nous l&rsquo;avons bien avant que vous ne vous donniez du mal pour l&rsquo;obtenir vous-même ou que vous laissiez quelqu&rsquo;un d&rsquo;autre l&rsquo;utiliser sans savoir combien il en utilise !</p>\n<p>Trouver votre numéro de téléphone fixe est facile et peut être fait rapidement. La meilleure façon de procéder est de vous appeler d&rsquo;un autre téléphone ou de vérifier votre identification de l&rsquo;appelant si vous en avez une. Si cela ne fonctionne pas pour une raison quelconque, cherchez votre numéro dans les pages blanches ou en ligne si vous disposez d&rsquo;une connexion Internet à la maison. Enfin, appelez votre fournisseur de services si tout le reste échoue !</p>",
 "readingTime": 3,
 "faq": [],
 "regenerated": false
}