{
 "id": 2911,
 "slug": "comment-choisir-des-ceramiques-pour-une-salle-de-bain-avec-un-eclairage-specifique",
 "title": "Comment choisir des céramiques pour une salle de bain avec un éclairage spécifique ?",
 "date": "2024-11-17T09:52:16",
 "modified": "2024-11-17T09:52:19",
 "excerpt": "Choisir des céramiques adaptées à une salle de bain requiert une attention particulière à l’éclairage ambiant. Chaque type de lumière influence la perception des couleurs et des textures. Un éclairage tendre et diffus mettra en valeur des nuances douces, tandis qu’une lumière intense et ciblée souli",
 "image": "/media/2911.webp",
 "imageAlt": "Comment choisir des céramiques pour une salle de bain avec un éclairage spécifique ?",
 "category": "infos",
 "tags": [],
 "html": "<p>Choisir des céramiques adaptées à une salle de bain requiert une attention particulière à l’éclairage ambiant. Chaque type de lumière influence la perception des couleurs et des textures. Un éclairage <strong>tendre et diffus</strong> mettra en valeur des nuances douces, tandis qu’une lumière <strong>intense et ciblée</strong> soulignera les détails des motifs.<br />\nLes salles de bain à faible luminosité nécessitent des carrelages <strong>clairs et réfléchissants</strong> pour maximiser la luminosité. L’harmonie entre le choix des céramiques et l’éclairage assure non seulement <strong>esthétique</strong> mais aussi <strong>fonctionnalité</strong> dans cette pièce dédiée au bien-être. Opter pour des céramiques et des solutions lumineuses adaptées transforme chaque espace en une expérience sensorielle unique.</p>\n<figure>\n<table>\n<tbody>\n<tr>\n<td>Résumé express</td>\n</tr>\n<tr>\n<td><strong>Évaluer l’éclairage</strong> : Comprendre le type d’éclairage (naturel et artificiel) présent dans la salle de bain.</td>\n</tr>\n<tr>\n<td><strong>Choisir des couleurs claires</strong> : Les céramiques de teintes claires reflètent mieux <strong>la lumière</strong> et agrandissent visuellement l’espace.</td>\n</tr>\n<tr>\n<td><strong>Brevets et finitions</strong> : Opter pour des céramiques avec des finitions <strong>brillantes</strong> pour maximiser la réflexion de la lumière.</td>\n</tr>\n<tr>\n<td><strong>Associer les matériaux</strong> : Harmoniser le choix des céramiques avec le style d’éclairage pour une ambiance cohérente.</td>\n</tr>\n<tr>\n<td><strong>Indice de Rendu des Couleurs (IRC)</strong> : Sélectionner des sources de lumière avec un IRC élevé pour une meilleure perception des couleurs des céramiques.</td>\n</tr>\n<tr>\n<td><strong>Éclairage ciblé</strong> : Installer des luminaires au-dessus des zones stratégiques comme le lavabo pour mettre en valeur le <strong>carrelage</strong>.</td>\n</tr>\n<tr>\n<td><strong>Considérer la taille des carreaux</strong> : Des carreaux plus grands peuvent éviter des ombres et créer une <strong>illusion d’espace</strong>.</td>\n</tr>\n<tr>\n<td><strong>Avis de sécurité</strong> : Choisir des céramiques antidérapantes pour assurer la sécurité, surtout dans des zones humides.</td>\n</tr>\n</tbody>\n</table>\n</figure>\n<h2>Choisir des céramiques en fonction de l’éclairage de la salle de bain</h2>\n<p>La sélection de <strong>céramiques</strong> pour une salle de bain doit prendre en compte l’éclairage qui prévaut dans cet espace. Les céramiques claires et réfléchissantes se révèlent particulièrement adaptées pour les salles de bain disposant d’un éclairage faible. Elles contribuent à maximiser la luminosité, en renvoyant la lumière au lieu de l’absorber. Ainsi, un carrelage en porcelaine ou en faïence avec une finition brillante apportera une touche de clarté bienvenue.</p>\n<h2>Les teintes et motifs à privilégier</h2>\n<p>Le choix des teintes joue un rôle fondamental dans l’harmonisation de l’éclairage. Les couleurs claires, telles que le blanc, le beige ou les pastel, créent une ambiance apaisante et contribuent à refléter la lumière. Les motifs subtiles, tels que des textures douces ou des dessins géométriques, ajoutent de l’élégance sans assombrir l’espace. À l’inverse, des céramiques sombres absorbent la lumière, ce qui peut donner une impression d’étouffement dans des salles de bain peu éclairées.</p>\n<h2>La finition: un élément essentiel</h2>\n<p>La finition du carrelage influence aussi la perception de la lumière. Une finition brillante permet à la lumière de rebondir efficacement, tandis qu’une finition mate, bien que séduisante, peut rendre la salle de bain plus sombre. Les céramiques à effet satiné combinent les avantages des deux finitions, offrant une réflexion douce qui maintient une ambiance chaleureuse tout en gardant une certaine luminosité.</p>\n<h2>L’importance de l’éclairage artificiel</h2>\n<p>La présence d’un éclairage artificiel adéquat vient compléter le choix des céramiques. Pour une efficacité maximale, viser près de <strong>300 lumens par mètre carré</strong> pour les zones principales de circulation, et environ <strong>100 lumens par mètre carré</strong> pour créer une atmosphère tamisée. Une lumière bien pensée autour des miroirs, à l’aide d’appliques ou de réglette LED, offre à la fois fonctionnalité et esthétisme.</p>\n<h2>Le choix des luminaires</h2>\n<p>Les luminaires, par leur conception, doivent également s’intégrer harmonieusement avec le carrelage. Opter pour des lumières à <strong>température de couleur</strong> élevée, telles que les ampoules à <strong>4000 kelvins</strong>, peut rehausser les nuances des céramiques. Les lampes à <strong>indice de rendu de couleur (IRC)</strong> supérieur à 80 garantissent une restitution fidèle des couleurs, tout en rehaussant les détails des matériaux.</p>\n<h2>Les contraintes d’un espace restreint</h2>\n<p>Dans une salle de bain à l’espace limité, choisir des céramiques qui semblent agrandir l’espace s’avère judicieux. Des motifs verticaux ou des carreaux de grande taille peuvent donner une illusion de hauteur, tandis que des carreaux clairs aux bords légèrement arrondis créent une atmosphère plus douce. L’utilisation de miroirs stratégiquement placés amplifie la lumière et donne une impression d’ouverture.</p>\n<h2>Intégrer des éléments de décoration</h2>\n<p>Afin d’enrichir visuellement un espace tout en restant adapté à l’éclairage, mélanger des céramiques avec d’autres matériaux, comme le bois ou le métal, ajoute une touche de modernité. Par exemple, des éléments décoratifs en bois, accentués par des céramiques brillantes, apporte une dynamique chaleureuse, tout en gardant une structure élégante.</p>\n<figure>\n<div><iframe loading=\"lazy\" title=\"Comment choisir le MIROIR idéal pour votre salle de bains ?🪞\" src=\"https://www.youtube.com/embed/LQTgw2HVDO0?feature=oembed\" width=\"500\" height=\"281\" frameborder=\"0\" allowfullscreen=\"allowfullscreen\"></iframe></div>\n</figure>\n<h2>Questions fréquentes sur le choix de céramiques pour une salle de bain avec un éclairage spécifique</h2>\n<p><strong>Comment choisir la couleur des céramiques en fonction de l’éclairage de ma salle de bain ?</strong><br />\n<i>Il est recommandé d’opter pour des céramiques claires dans les salles de bain peu éclairées, car elles réfléchissent mieux la lumière et contribuent à illuminer l’espace. Des tons de blanc, beige ou pastel sont idéaux.</i><br />\n<strong>Quels types de finitions de céramiques privilégier pour créer une ambiance lumineuse ?</strong><br />\n<i>Les finitions brillantes ou satinées des céramiques sont à privilégier, car elles réfléchissent la lumière de manière optimale, créant une ambiance plus lumineuse et aérée.</i><br />\n<strong>Comment sélectionner des céramiques résistantes à l’humidité tout en tenant compte de l’éclairage ?</strong><br />\n<i>Il est essentiel de choisir des céramiques conçues pour les environnements humides. Assurez-vous qu’elles possèdent un faible taux d’absorption d’eau et vérifiez la norme d’étanchéité.</i><br />\n<strong>Quelle taille de carreaux choisir en fonction de la luminosité de la salle de bain ?</strong><br />\n<i>Pour des espaces restreints ou avec peu de lumière naturelle, il est conseillé d’opter pour des carreaux de grande taille, car ils réduisent les lignes de joint et donnent une impression de profondeur.</i><br />\n<strong>Comment intégrer l’éclairage dans le choix de mes céramiques ?</strong><br />\n<i>Pensez à l’intégration d’éclairages directs et indirects. Par exemple, des luminaires placés au-dessus des miroirs peuvent accentuer les céramiques sélectionnées et créer un effet visuel harmonieux.</i><br />\n<strong>Quelle est l’importance de la texture des céramiques dans une salle de bain ?</strong><br />\n<i>La texture joue un rôle crucial, surtout en matière de sécurité. Optez pour des céramiques anti-dérapantes pour les zones humides, tout en gardant à l’esprit le contraste de texture à travers les différentes surfaces.</i><br />\n<strong>Comment le choix des céramiques peut-il influencer la perception de l’espace ?</strong><br />\n<i>Des céramiques claires et brillantes agrandissent visuellement l’espace, tandis que des céramiques sombres peuvent le rendre plus intimiste. Considérez l’effet désiré lors de votre sélection.</i><br />\n<strong>Quel éclairage choisir pour mettre en valeur les céramiques ?</strong><br />\n<i>Des ampoules LED à lumière froide (4000 Kelvin) sont idéales pour faire ressortir les couleurs et la brillance des céramiques. Évitez les éclairages trop chauds qui peuvent altérer les teintes.</i></p>",
 "readingTime": 5,
 "faq": [],
 "regenerated": false
}