{
 "id": 178,
 "slug": "gps-marine-pourquoi-opter-pour-le-gps-marine",
 "title": "GPS marine : Pourquoi opter pour le GPS Marine ?",
 "date": "2018-09-20T17:23:13",
 "modified": "2023-12-27T12:18:23",
 "excerpt": "Le gis marine est la meilleure solution de guidage avant de pouvoir partir en randonnée dans la montagne. En effet ce GPS est fait pour les parcours qui sont longs et qui demandent aussi du temps dans la préparation. Le gps marine permet une localisation de la personne grâce à un signal de qualité. ",
 "image": "/media/178.webp",
 "imageAlt": "GPS marine : Pourquoi opter pour le GPS Marine ?",
 "category": "infos",
 "tags": [],
 "html": "<p>Le gis marine est la meilleure solution de guidage avant de pouvoir partir en randonnée dans la montagne. </p>\n<p>En effet ce GPS est fait pour les parcours qui sont longs et qui demandent aussi du temps dans la préparation. <strong>Le gps marine permet une localisation de la personne grâce à un signal de qualité. </strong>Sans oublier que ce GPS marine est la solution pour divers marcheurs ou bien des cyclistes qui auraient envie de partir à vélo. </p>\n<p>En effet il faut savoir que les cyclistes ont beaucoup de chance de pouvoir proposer un parcours à vélo qui soit cohérent et important. Sans oublier que le vélo est le sport de référence du week-end pour beaucoup de Français. </p>\n<ul>\n<li>Un GPS de taille</li>\n<li>Un petit GPS</li>\n<li>Un GPS exceptionnel</li>\n</ul>\n<p>Il est évident que le vélo peut créer les conditions pour acheter un GPS marine. </p>\n<h2>Un GPS de qualité</h2>\n<p> Le GPS marine n’est pas à son coup d’essai. </p>\n<p>Très utilisé par les cyclistes pour avoir des données qui sont importantes pour eux lors du parcours à vélo. <strong>Le GPS marine est simplement la sensation en matière d’orientation. En effet équipé d’un système de cartographie qui est très impressionnant, le GPS marine a tout compris sur ce que l’on attendait de lui. </strong>Il est très intéressant de mettre une idée en place. Il est vrai que ce GPS est unique en France. C’est l’un des outils qui peut servir pour la bonne gestion du parcours.</p>",
 "readingTime": 3,
 "faq": [],
 "regenerated": false
}