{
 "id": 1701,
 "slug": "les-projets-diy-pour-transformer-des-objets-du-quotidien-en-art",
 "title": "Les projets DIY pour transformer des objets du quotidien en art",
 "date": "2023-12-11T07:35:11",
 "modified": "2023-12-27T12:17:42",
 "excerpt": "Transformer des objets du quotidien en art par le biais de projets DIY (Do It Yourself) est une manière imaginative et écologique d’embellir votre environnement tout en exprimant votre créativité. Souvent méconnus, ces petits actes de réinvention offrent une seconde vie à nos objets habituels, ainsi",
 "image": "/media/1701.webp",
 "imageAlt": "Les projets DIY pour transformer des objets du quotidien en art",
 "category": "infos",
 "tags": [],
 "html": "<p>Transformer des objets du quotidien en art par le biais de projets DIY (Do It Yourself) est une manière imaginative et écologique d’embellir votre environnement tout en exprimant votre créativité. Souvent méconnus, ces petits actes de réinvention offrent une seconde vie à nos objets habituels, ainsi qu’une touche personnelle à notre décoration intérieure. Ces projets constituent un excellent moyen de stimuler votre inventivité, de réduire les déchets et d’ajouter une dimension artistique à votre foyer.</p>\n<h2>Un Monde de Possibilités pour Upcycler avec Ingéniosité</h2>\n<p>Upcycler, ou l’art de recycler « par le haut », signifie valoriser un objet en lui donnant une nouvelle fonction, souvent plus créative et esthétique. Les possibilités sont infinies face à la pléthore d’objets que nous possédons. Jetons un coup d’œil à quelques-uns de ces projets qui allient utilité et esthétique.</p>\n<h3>Réinventez vos Meubles pour une Touche Unique</h3>\n<p>Les meubles sont les toiles idéales pour exprimer votre créativité. Par exemple, une simple chaise peut devenir une œuvre d’art avec un peu de peinture et quelques motifs bien choisis. Utilisez de la peinture acrylique ou des pochoirs pour créer des designs uniques sur vos tables, étagères ou commodes. Ajoutez des boutons de porte fantaisistes ou des pieds sculptés pour transformer un meuble banal en pièce maîtresse.</p>\n<h3>Donnez Vie à des Objets Inanimés</h3>\n<p>Avez-vous déjà pensé à transformer une vieille échelle en étagère murale florale? Ou bien des bouteilles en verre en lampes féeriques? Ces détournements d’objets apportent non seulement un cachet artistique à votre intérieur mais participent également à une démarche écoresponsable. Osez peindre, découper, coller et assembler pour donner un second souffle à ces objets du quotidien.</p>\n<h3>Le Textile au Cœur de la Créativité</h3>\n<p>Les textiles offrent une toile de fond variée pour des œuvres d’art DIY. Une ancienne nappe peut être transformée en toile pour peinture, ou des draps usés en rideaux bohèmes teints à la main. Même vieux vêtements peuvent se muer en tapis ou en coussins colorés, augmentant ainsi leur durée de vie et réduisant la consommation inutile.</p>\n<h2>Conseils pour un Projet d’Upcycling Réussi</h2>\n<p>Pour un projet d’upcycling réussi, quelques astuces sont indispensables:</p>\n<ul>\n<li><strong>Planifiez votre projet</strong>: Avant de commencer, ayez une idée claire de ce que vous voulez créer. Faites un croquis ou listez les étapes pour garder le cap sur votre vision.</li>\n<li><strong>Préparez votre espace de travail</strong>: Assurez-vous d’avoir tous les outils et matériels nécessaires. Travaillez dans un espace bien ventilé et protégé, surtout si vous utilisez de la peinture ou de la colle.</li>\n<li><strong>Privilégiez la qualité</strong>: Choisissez des matériaux de bonne qualité pour votre projet. Même si l’idée est de recycler, l’objet transformé doit rester fonctionnel et résistant.</li>\n<li><strong>Soyez patient</strong>: Les plus belles créations demandent du temps. Laissez libre cours à votre créativité sans vous presser pour obtenir un résultat dont vous serez fier.</li>\n</ul>\n<h2>Des Projets DIY pour Valoriser et Inspirer</h2>\n<p>La réinvention d’objets a aussi un impact sur notre vision du monde. En transformant le quotidien en art, nous prenons conscience de la valeur intrinsèque des choses et de leur potentiel caché. Ces projets DIY stimulent non seulement notre créativité mais deviennent aussi des déclarations personnelles dans notre maison. Ils inspirent ceux qui nous entourent et favorisent une approche plus réfléchie de la consommation.</p>\n<p>Pensez à partager vos créations sur les réseaux sociaux ou lors d’ateliers communautaires. Le partage de vos réalisations peut inciter d’autres à se lancer dans l’aventure de l’upcycling, créant ainsi une communauté de passionnés de DIY et de défenseurs de l’environnement.</p>\n<h2>Un Art Accessible et Source de Bien-Être</h2>\n<p>Allier l’utile à l’agréable et transformer des objets usuels en art sont des activités à la portée de tous. Elles permettent non seulement de personnaliser son espace de vie mais favorisent également un bien-être psychologique. En effet, la création artistique a été liée à une réduction du stress et à l’amélioration de l’humeur.</p>\n<p>Commencez petit, avec des projets simples, et peu à peu, vous verrez vos compétences et votre audace grandir. Le DIY est une belle aventure, aussi bien pour l’esprit inventif que pour l’âme artistique qui sommeille en chacun de nous.</p>\n<p>Les aventures DIY offrent un potentiel illimité pour personnaliser nos intérieurs et notre monde. Elles sont une preuve que l’art n’est pas l’apanage des galeries et musées; il peut être créé et apprécié dans le confort de notre foyer. Pour tous ceux qui cherchent à exprimer leur identité à travers leur environnement, la transformation d’objets quotidien en art est une voie royale. Embarquez dans cette démarche créative et voyez comment vos idées peuvent enchanter et révolutionner votre espace personnel tout en promouvant la durabilité!</p>",
 "readingTime": 3,
 "faq": [],
 "regenerated": false
}