{
 "id": 297,
 "slug": "mouche-bebe-electrique-pourquoi-faut-il-se-munir-dun-mouche-bebe-electrique",
 "title": "Mouche bébé électrique : pourquoi faut-il se munir d’un mouche bébé électrique ?",
 "date": "2018-03-27T12:08:04",
 "modified": "2023-12-27T12:18:32",
 "excerpt": "Un petit bébé nourrisson ne pourra jamais se moucher tout seul, il lui faut un bon mouche bébé et de préférence un mouche bébé électrique. Le bébé doit être bien surveillé et ne pas être laisser avec des mucosités qui risquent de l&rsquo;encombrer. Vous voulez acheter un bon mouche bébé électrique ?",
 "image": "/media/297.webp",
 "imageAlt": "Mouche bébé électrique : pourquoi faut-il se munir d’un mouche bébé électrique ?",
 "category": "infos",
 "tags": [],
 "html": "<p>Un petit bébé nourrisson ne pourra jamais se moucher tout seul, il lui faut un bon mouche bébé et de préférence un mouche bébé électrique. <strong>Le bébé doit être bien surveillé et ne pas être laisser avec des mucosités qui risquent de l&rsquo;encombrer.</strong></p>\n<p>Vous voulez acheter un bon mouche bébé électrique ? Vous hésitez à vous en procurez un ?</p>\n<p>Voyons ensemble pourquoi vous devez l’acheter ?</p>\n<p>Pour plus d’informations nous vous invitons à visiter notre site https://www.mouche-bebe-electrique.fr</p>\n<h2>Pourquoi faut-il avoir un mouche bébé électrique ?</h2>\n<p> Vous aurez à utiliser un mouche bébé électrique très souvent, pour cela il vous faut avoir un et savoir le choisir . votre mouche bébé électrique va vous permettre de <strong>débarrasser votre bébé des mucosités qui le gênent  </strong>et ainsi de soulager votre enfant  en lui facilitant sa respiration.</p>\n<p>Le mouche bébé électrique va éviter à votre bébé de développer une infection ou bien des complications dues à l’accumulation des mucosité sans oublier que ça va permettre à votre bébé d’avoir un sommeil confortable.</p>\n<p>Autres avantages du mouche bébé électrique :</p>\n<ul>\n<li>Votre bébé va retrouver le sourire car devient plus à l’aise.</li>\n<li>Il facilite aux parents l’opération surtout pour des parents peureux.</li>\n</ul>",
 "readingTime": 3,
 "faq": [],
 "regenerated": false
}