{
 "id": 2498,
 "slug": "pourquoi-est-ce-que-ca-compte-pour-moi",
 "title": "Pourquoi est-ce que ça compte pour moi ?",
 "date": "2024-07-28T11:12:16",
 "modified": "2024-07-28T11:12:19",
 "excerpt": "Pourquoi est-ce important pour moi ? Pourquoi est-ce que ça compte pour moi ? Pourquoi est-ce important pour moi ? Imaginez-vous un instant dans la peau de quelqu’un capable de saisir l’importance personnelle des sujets qui l’entourent. Pourquoi, me direz-vous ? Parce que comprendre pourquoi quelque",
 "image": "/media/2498.webp",
 "imageAlt": "Pourquoi est-ce que ça compte pour moi ?",
 "category": "infos",
 "tags": [],
 "html": "<h2>Pourquoi est-ce important pour moi ?</h2>\n<p>Pourquoi est-ce que ça compte pour moi ?</p>\n<p>Pourquoi est-ce important pour moi ?</p>\n<p>Imaginez-vous un instant dans la peau de quelqu’un capable de saisir l’importance personnelle des sujets qui l’entourent. Pourquoi, me direz-vous ? Parce que comprendre pourquoi quelque chose compte pour vous peut faire toute la différence dans votre vie quotidienne. Voici pourquoi vous devriez prêter attention à l’impact personnel des sujets qui vous concernent :</p>\n<ul>\n<li><strong>Engagement :</strong> Lorsque vous réalisez l’importance profonde d’un sujet pour vous-même, vous vous engagez naturellement davantage dans son exploration et sa compréhension.</li>\n<li><strong>Alignement :</strong> En identifiant ce qui résonne vraiment avec vous, vous pouvez mieux aligner vos actions, vos choix et vos décisions sur ce qui compte réellement pour vous.</li>\n<li><strong>Satisfaction :</strong> En accordant de l’importance aux sujets qui vous touchent personnellement, vous pouvez ressentir une satisfaction plus profonde et durable dans vos accomplissements.</li>\n</ul>\n<p>En somme, comprendre pourquoi un sujet est important pour vous peut vous aider à mieux vous investir, à mieux vous orienter et à mieux vous épanouir. Alors, pourquoi ne pas prendre le temps de réfléchir à ce qui compte vraiment pour vous aujourd’hui ?</p>\n<h3>Raison 1</h3>\n<p>Pourquoi est-ce que ça compte pour moi ?</p>\n<p>Pourquoi est-ce important pour moi ?</p>\n<p>Quand on parle de sujets importants, il est essentiel de se demander en quoi cela compte pour nous, personnellement. <strong>Comprendre l’impact direct </strong>que cela peut avoir sur notre vie quotidienne, notre travail ou nos passions peut changer notre perspective.</p>\n<h3>Raison 2</h3>\n<p>Pourquoi est-ce important pour moi ?</p>\n<p><strong>Raison 1:</strong> Il est essentiel de comprendre l’impact direct que ce sujet a sur ma vie quotidienne. En identifiant les avantages concrets que cela apporte à mes activités, je peux mieux saisir son importance.</p>\n<p><strong>Raison 2:</strong> La relation entre ce sujet et mes objectifs personnels ne doit pas être sous-estimée. En évaluant en quoi il contribue à mon épanouissement ou à l’atteinte de mes aspirations, je peux lui accorder toute l’attention qu’il mérite.</p>\n<p><strong>Raison 3:</strong> La connexion entre ce sujet et mes valeurs profondes joue un rôle crucial dans sa signification pour moi. En le reliant à ce qui est fondamental à mes yeux, je peux en mesurer l’impact réel sur mon bien-être et mes choix.</p>\n<h3>Raison 3</h3>\n<p>Pourquoi est-ce que ça compte pour moi ?</p>\n<p><strong>Raison 1 :</strong> Lorem ipsum dolor sit amet, consectetur adipiscing elit. Integer vitae arcu eu metus convallis ultricies. Sed vel sapien et nunc ultricies euismod.</p>\n<p><strong>Raison 2 :</strong> Duis ac augue a elit bibendum interdum. Vestibulum nec urna eu odio consequat vehicula ac a ipsum. Vivamus suscipit ligula id sapien finibus, vel porttitor orci malesuada.</p>\n<p><strong>Raison 3 :</strong></p>\n<ul>\n<li>Phasellus vel ante quis purus fringilla dignissim.</li>\n<li>Nulla facilisi. Sed euismod quam ac urna vestibulum, vel gravida libero tempor.</li>\n<li>Etiam nec arcu non sem fringilla aliquam.</li>\n</ul>\n<h2>Impact positif sur ma vie</h2>\n<p>Savez-vous pourquoi certains sujets sont si importants pour vous ? Pourquoi cela a-t-il un impact direct sur votre vie quotidienne ?</p>\n<p><strong>L’impact positif sur ma vie</strong></p>\n<p>1. <strong>Amélioration de votre quotidien :</strong> Les sujets qui vous tiennent à cœur peuvent grandement influencer votre bien-être au quotidien. Que ce soit en gérant efficacement votre travail, en trouvant des solutions pratiques pour votre famille ou en prenant soin de vous, ces sujets ont un impact direct sur votre bonheur et votre équilibre.</p>\n<p>2. <strong>Boost de motivation :</strong> Lorsque vous vous investissez dans des sujets qui vous importent, vous ressentez une vague de motivation et d’énergie. Cela peut vous pousser à réaliser vos objectifs professionnels et personnels avec enthousiasme et détermination.</p>\n<p>3. <strong>Évolution personnelle :</strong> En explorant des sujets qui vous passionnent, vous avez l’opportunité de vous développer personnellement. Que ce soit en acquérant de nouvelles compétences, en élargissant votre champ de connaissances ou en affinant votre sens critique, ces sujets peuvent vous aider à évoluer en tant qu’individu.</p>\n<p>4. <strong>Connexions significatives :</strong> Les sujets qui comptent pour vous peuvent également vous permettre de tisser des liens profonds avec d’autres personnes partageant vos intérêts. Ces connexions peuvent enrichir votre vie sociale et professionnelle, vous offrant un réseau de soutien et d’échanges précieux.</p>\n<p>En conclusion, les sujets qui ont un impact direct sur votre vie sont bien plus que de simples préoccupations. Ils sont le reflet de vos valeurs, de vos passions et de vos objectifs. En leur accordant de l’importance, vous donnez une dimension supplémentaire à votre existence et vous vous engagez pleinement dans la construction d’une vie qui vous ressemble.</p>\n<h3>Amélioration de la santé</h3>\n<p><strong>L’impact positif sur ma vie</strong></p>\n<p>Quand on parle de sujets importants, il est crucial de se demander en quoi cela peut influencer notre existence quotidienne. L’un des aspects les plus significatifs est l’<strong>amélioration de la santé</strong>. Prendre soin de son corps et de son esprit est essentiel pour mener une vie épanouie et productive.</p>\n<p><strong>Amélioration de la santé</strong></p>\n<p>Prendre des mesures pour améliorer sa santé impacte positivement notre bien-être global. Que ce soit en adoptant une alimentation équilibrée, en pratiquant une activité physique régulière ou en prenant soin de notre santé mentale, chaque geste compte et contribue à notre qualité de vie.</p>\n<p>Voici quelques bénéfices concrets liés à l’<strong>amélioration de la santé</strong>:</p>\n<ul>\n<li>Une meilleure énergie au quotidien</li>\n<li>Une diminution du stress et de l’anxiété</li>\n<li>Une meilleure qualité de sommeil</li>\n<li>Une réduction des risques de maladies</li>\n</ul>\n<h3>Augmentation du bonheur</h3>\n<p>Pourquoi est-ce que ça compte pour moi ?</p>\n<p>Impact positif sur ma vie</p>\n<p>Augmentation du bonheur</p>\n<p>Il est essentiel de comprendre l’importance des sujets qui nous entourent et qui impactent notre quotidien. En se concentrant sur les aspects qui ont un réel impact sur notre vie, on peut augmenter notre bonheur et notre satisfaction personnelle.</p>\n<p>Lorsque l’on prend le temps de se questionner sur l’impact de certaines décisions ou actions, on se rend compte que chaque choix compte. Ces petits détails ont un effet cumulatif sur notre bien-être global.</p>\n<p>Voici quelques raisons pour lesquelles il est crucial de se pencher sur les sujets qui importent vraiment :</p>\n<ul>\n<li><strong>Amélioration de la qualité de vie quotidienne</strong>: En identifiant ce qui nous tient à cœur et en y accordant de l’importance, on peut améliorer notre quotidien et rendre chaque journée plus agréable.</li>\n<li><strong>Renforcement des relations personnelles</strong>: En exprimant nos valeurs et nos préoccupations, on crée des liens plus forts avec les autres et on favorise des interactions plus enrichissantes.</li>\n<li><strong>Accomplissement de soi</strong>: En se concentrant sur ce qui compte vraiment pour nous, on se rapproche de nos buts et de nos aspirations, ce qui nous permet de nous épanouir pleinement.</li>\n</ul>\n<p>En conclusion, se pencher sur les sujets qui comptent vraiment pour nous est un moyen efficace d’améliorer notre qualité de vie et notre bonheur global. Prendre conscience de l’impact de nos choix et de nos actions nous aide à avancer dans la bonne direction et à cultiver un sentiment de satisfaction personnelle profonde.</p>\n<h3>Renforcement des relations</h3>\n<p>Il est essentiel de se questionner sur l’importance personnelle des sujets qui nous entourent. Que ce soit dans notre vie professionnelle ou personnelle, chaque élément a un impact sur notre quotidien. <strong>En prenant conscience de cette dimension personnelle</strong>, nous pouvons mieux appréhender les sujets qui nous concernent.</p>\n<p>Un aspect important à considérer est l’impact positif que peuvent avoir certaines actions ou décisions sur notre vie. <strong>En identifiant ces aspects positifs</strong>, nous sommes plus enclins à nous investir pleinement dans ce que nous entreprenons.</p>\n<ul>\n<li>Une meilleure santé</li>\n<li>Une amélioration de nos relations</li>\n<li>Une plus grande satisfaction personnelle</li>\n</ul>\n<p>Un autre point à ne pas sous-estimer est le renforcement des relations que peuvent apporter certains sujets. <strong>En cultivant ces relations</strong>, nous enrichissons notre vie sociale et professionnelle.</p>\n<p>En conclusion, interroger et comprendre pourquoi un sujet compte pour nous est crucial pour notre épanouissement personnel. <strong>En prenant le temps de réfléchir à ces aspects</strong>, nous pouvons mieux orienter nos actions et décisions pour une vie plus épanouissante.</p>\n<figure>\n<table>\n<tbody>\n<tr>\n<td>?</td>\n<td>Cela me permet de me dépasser et d’atteindre mes objectifs personnels.</td>\n</tr>\n<tr>\n<td>?</td>\n<td>Cela renforce ma confiance en moi et ma résilience face aux obstacles.</td>\n</tr>\n<tr>\n<td>?</td>\n<td>Cela contribue à mon développement personnel et à mon épanouissement.</td>\n</tr>\n<tr>\n<td>?</td>\n<td>Cela me procure une satisfaction et un bien-être intérieur.</td>\n</tr>\n<tr>\n<td>?</td>\n<td>Cela m’apporte de nouvelles perspectives et des apprentissages enrichissants.</td>\n</tr>\n</tbody>\n</table>\n</figure>\n<h2>Comment démarrer</h2>\n<p>Pourquoi est-ce que ça compte pour moi ?</p>\n<p><strong>Comment démarrer</strong></p>\n<p>Lorsqu’il s’agit de sujets importants dans notre vie, il est essentiel de se poser la question : pourquoi est-ce que ça compte pour moi ? Cette réflexion personnelle peut nous aider à comprendre en profondeur l’impact et la valeur de certaines thématiques dans notre quotidien.</p>\n<p>Pour démarrer cette démarche, il est primordial de prendre le temps de se connecter avec ses propres aspirations, ses besoins et ses valeurs. Se questionner sur ce qui nous motive profondément peut nous guider vers des choix et des décisions plus alignés avec qui nous sommes vraiment.</p>\n<p>Ensuite, il est également crucial de passer en revue les bénéfices que pourrait apporter ce sujet particulier dans notre vie. Identifier les avantages tangibles ou même émotionnels peut renforcer notre engagement et notre intérêt pour la question en question.</p>\n<p>Enfin, ne pas hésiter à explorer les liens entre ce sujet et nos objectifs à court, moyen et long terme. En comprenant comment cela s’inscrit dans notre trajectoire personnelle, nous pouvons donner encore plus de sens et de pertinence à notre implication.</p>\n<h3>Fixer des objectifs clairs</h3>\n<p><strong>Pourquoi est-ce que ça compte pour moi ?</strong></p>\n<p>Fixer des objectifs clairs</p>\n<h3>Établir un plan d’action</h3>\n<p><strong>Comment démarrer</strong></p>\n<p>Pour commencer sur la voie de la réussite, il est essentiel d’établir un plan d’action clair et efficace. Voici quelques étapes à suivre :</p>\n<p><strong>Établir un plan d’action</strong></p>\n<ul>\n<li>Identifiez vos objectifs prioritaires</li>\n<li>Évaluez vos ressources disponibles et nécessaires</li>\n<li>Définissez des étapes réalisables pour atteindre vos objectifs</li>\n<li>Allouez du temps à chaque tâche pour rester focalisé</li>\n<li>Assurez-vous de suivre votre progression régulièrement</li>\n</ul>\n<h3>Suivre ses progrès</h3>\n<p><strong>Pourquoi est-ce que ça compte pour moi ?</strong></p>\n<p><strong>Comment démarrer</strong></p>\n<p>Si vous vous demandez comment aborder un nouveau projet ou une nouvelle tâche, la première étape consiste à définir vos objectifs. Il est essentiel de savoir ce que vous souhaitez accomplir pour pouvoir mettre en place une stratégie efficace.</p>\n<p>Ensuite, identifiez les étapes à suivre pour atteindre ces objectifs. Divisez le processus en tâches plus petites et plus gérables, ce qui vous permettra de rester organisé et de mesurer votre progression.</p>\n<p><strong>Suivre ses progrès</strong></p>\n<p>Pour rester motivé et productif, il est essentiel de suivre vos progrès régulièrement. Utilisez des outils de suivi ou créez des tableaux de bord pour visualiser votre avancement. Cela vous aidera à ajuster votre stratégie si nécessaire et à rester sur la bonne voie.</p>\n<h2>Conseils pratiques</h2>\n<figure>\n<div><iframe loading=\"lazy\" title=\"C'est quoi vivre ensemble ? - 1 jour, 1 question\" src=\"https://www.youtube.com/embed/pLDZ7dD2sLc?feature=oembed\" width=\"1290\" height=\"726\" frameborder=\"0\" allowfullscreen=\"allowfullscreen\"></iframe></div>\n</figure>\n<figure>\n<div>\n<blockquote>\n<p dir=\"ltr\" lang=\"fr\">Les noms ont pour seule signification celle qu&rsquo;on leur donne.</p>\n<p>Comment votre escouade a-t-elle appelé cette rune de la Ruche ? <a href=\"https://t.co/9VlnUVxpVg\">pic.twitter.com/9VlnUVxpVg</a></p>\n<p>— Destiny 2 (@DestinyGameFR) <a href=\"https://twitter.com/DestinyGameFR/status/1678056427833655296?ref_src=twsrc%5Etfw\">July 9, 2023</a></p></blockquote>\n<p><script async src=\"https://platform.twitter.com/widgets.js\" charset=\"utf-8\"></script></p>\n</div>\n</figure>\n<p>Il est crucial de se poser la question de l’importance des sujets qui nous entourent. Pourquoi devrions-nous nous soucier de telle ou telle chose ? Comment ces sujets ont un impact direct sur notre quotidien ? Voici quelques conseils pratiques pour vous aider à valoriser et à comprendre l’importance personnelle des sujets qui vous concernent.</p>\n<p><strong>1. Identifier les avantages pour vous :</strong> Prenez le temps d’analyser en quoi le sujet en question peut vous apporter des avantages concrets. Que cela soit au niveau professionnel, personnel, ou même émotionnel, identifiez comment cela peut améliorer votre vie.</p>\n<p><strong>2. Faire le lien avec vos objectifs :</strong> Reliez le sujet à vos objectifs à court, moyen ou long terme. En comprenant comment il peut vous aider à atteindre vos buts, vous verrez son importance augmenter de manière significative.</p>\n<p><strong>3. Considérer les conséquences :</strong> Pesez le pour et le contre. Réfléchissez aux conséquences de ne pas accorder d’importance à ce sujet. Cela peut vous aider à prendre conscience de son véritable impact.</p>\n<p><strong>4. Se projeter dans l’avenir :</strong> Envisagez comment ce sujet pourrait affecter votre avenir. Que se passerait-il si vous négligiez sa pertinence ? Visualiser les scénarios possibles peut vous aider à mesurer son importance.</p>\n<h3>Éviter la procrastination</h3>\n<p>Il est facile de repousser les tâches importantes à plus tard, mais la procrastination peut avoir des conséquences négatives sur notre vie professionnelle et personnelle. Voici quelques conseils pratiques pour éviter de céder à cette tendance :</p>\n<ul>\n<li>Fixez-vous des objectifs clairs et atteignables.</li>\n<li>Divisez les tâches en petites étapes pour les rendre plus gérables.</li>\n<li>Utilisez un agenda ou un outil de gestion de tâches pour suivre vos progrès.</li>\n<li>Identifiez les distractions potentielles et trouvez des moyens de les éliminer.</li>\n</ul>\n<h3>Trouver un soutien</h3>\n<p>Pourquoi est-ce que <strong>ça compte pour moi</strong> ?</p>\n<p><strong>Trouver un soutien</strong></p>\n<p>Lorsque l’on se lance dans un nouveau projet ou que l’on rencontre des difficultés, il est essentiel de pouvoir trouver un soutien autour de soi. Que ce soit en discutant avec des proches, des collègues ou en faisant appel à des professionnels, le soutien moral et technique peut faire toute la différence.</p>\n<p>Voici quelques pistes pour trouver un soutien efficace :</p>\n<ul>\n<li>Identifier les personnes ressources dans votre entourage professionnel ou personnel</li>\n<li>Rejoindre des groupes ou des communautés en ligne partageant les mêmes centres d’intérêt</li>\n<li>Consulter des experts ou des coachs pour bénéficier de conseils adaptés à votre situation</li>\n</ul>\n<h3>Célébrer les petites victoires</h3>\n<p>Pourquoi est-ce que ça compte pour moi ?</p>\n<p>Il est essentiel de prendre le temps de célébrer les petites victoires dans notre quotidien. Que ce soit accomplir une tâche difficile, atteindre un objectif personnel ou simplement passer une journée agréable, chaque petite victoire mérite d’être reconnue.</p>\n<p>Voici quelques conseils pratiques pour intégrer cette pratique enrichissante dans votre vie :</p>\n<ul>\n<li><strong>Prenez le temps de savourer</strong> : Plutôt que de passer à la tâche suivante rapidement, arrêtez-vous un moment pour apprécier votre réussite. Cela renforce votre motivation et votre satisfaction personnelle.</li>\n<li><strong>Exprimez votre gratitude</strong> : Remerciez-vous pour vos efforts et trouvez des moyens de vous récompenser. Cela renforce la confiance en soi et vous encourage à poursuivre vos objectifs.</li>\n<li><strong>Célébrez avec les autres</strong> : Partagez vos petites victoires avec vos proches ou collègues. Leur soutien et encouragement renforcent le sentiment de réussite et créent des liens positifs.</li>\n</ul>\n<p>Célébrer les petites victoires contribue à créer une ambiance positive, à stimuler la motivation et à développer une attitude de gratitude. Prenez l’habitude de reconnaître et de célébrer ces moments qui jalonnent votre parcours, ils sont la clé d’un bien-être durable et d’une progression constante.</p>",
 "readingTime": 11,
 "faq": [],
 "regenerated": false
}