{
 "id": 1731,
 "slug": "techniques-efficaces-pour-la-meditation-en-marchant-maitriser-lart-de-la-pleine-conscience-en-mouvement-topic",
 "title": "Techniques efficaces pour la méditation en marchant : maîtriser l’art de la pleine conscience en mouvement {topic}",
 "date": "2023-12-27T09:58:23",
 "modified": "2023-12-27T12:17:41",
 "excerpt": "La méditation en marchant est une forme de méditation en pleine conscience qui allie le mouvement physique à la pratique méditative traditionnelle assise. Cette combinaison offre des avantages uniques, en engageant le corps et l&rsquo;esprit dans une expérience harmonieuse de présence et de calme. D",
 "image": "/media/1731.webp",
 "imageAlt": "Techniques efficaces pour la méditation en marchant : maîtriser l’art de la pleine conscience en mouvement {topic}",
 "category": "infos",
 "tags": [],
 "html": "<p>La méditation en marchant est une forme de méditation en pleine conscience qui allie le mouvement physique à la pratique méditative traditionnelle assise. Cette combinaison offre des avantages uniques, en engageant le corps et l&rsquo;esprit dans une expérience harmonieuse de présence et de calme. Dans le tumulte quotidien, méditer en marchant se révèle être une technique puissante pour revenir à l&rsquo;instant présent et trouver la paix intérieure.</p>\n<h2><strong>débuter avec la méditation en marchant</strong></h2>\n<p>Commencer la méditation en marchant nécessite un espace convenable où vous pouvez marcher sans entrave, idéalement dans la nature ou un endroit paisible. L&rsquo;habit ne fait pas le moine, mais une tenue confortable et des chaussures adaptées vous permettront de rester concentré sur votre pratique plutôt que sur un inconfort physique.</p>\n<h3><strong>préparation mentale et physique</strong></h3>\n<p><strong>Se préparer mentalement</strong>, c&rsquo;est d&rsquo;abord se donner la permission de ralentir, de mettre une pause dans ses préoccupations habituelles. Il est crucial d&rsquo;adopter une intention de pleine présence, en acceptant de laisser de côté jugements et attentes le temps de la pratique.</p>\n<p><strong>Physiquement</strong>, commencez par quelques respirations profondes, en vous concentrant sur la sensation de l&rsquo;air qui entre et sort de vos poumons. C&rsquo;est un moyen efficace pour signaler à votre corps et à votre esprit que vous entrez dans un état méditatif.</p>\n<h3><strong>le processus de méditation en marchant</strong></h3>\n<p>Lorsque vous commencez à marcher, faites-le à un rythme plus lent que votre marche habituelle. L&rsquo;attention doit être portée sur chacun de vos pas, en sentant comment vos pieds touchent le sol, la répartition du poids du corps, et le mouvement de vos jambes.</p>\n<p><strong>Concentration sur la Respiration</strong> est souvent le fondement de la méditation. En marchant, synchronisez vos pas avec votre respiration. Par exemple, faites trois pas pendant que vous inspirez, et trois autres en expirant. Cette technique aide à maintenir l&rsquo;attention centrée.</p>\n<p><strong>Utilisation des Mantras</strong> : Répéter un mantra ou une phrase positive peut augmenter la concentration et améliorer l&rsquo;expérience globale de la méditation en marchant. Choisir des mots qui résonnent personnellement avec vous aura un effet plus profond.</p>\n<h3><strong>pleine conscience et sensations corporelles</strong></h3>\n<p>La <strong>pleine conscience des sensations</strong> est une méthode qui consiste à porter une attention détaillée à ce que vous ressentez physiquement pendant que vous marchez. Cela inclut les textures sous vos pieds, la température de l&rsquo;air, le vent sur votre peau, ou le mouvement de vos vêtements contre votre corps.</p>\n<h3><strong>variétés de parcours</strong></h3>\n<p>Varier les parcours peut enrichir votre pratique. Changer de terrain, que ce soit sur un sentier forestier, une plage, ou même dans un parc urbain, peut apporter de nouvelles sensations et favoriser un état de pleine conscience renouvelé.</p>\n<h3><strong>gestion des distractions</strong></h3>\n<p>Les distractions sont inévitables, mais elles peuvent être gérées. Lorsque vos pensées vagabondent ou que des stimuli externes vous éloignent de votre concentration, reconnaître simplement ces interruptions et les laisser passer comme des nuages dans le ciel vous permettra de revenir doucement à votre méditation.</p>\n<h3><strong>approfondir sa pratique</strong></h3>\n<p>Avec le temps, comme toute compétence, la méditation en marchant peut être approfondie. Intégrer des visualisations apaisantes ou des exercices de gratitude pendant votre marche peut augmenter l&rsquo;intensité de votre expérience méditative.</p>\n<h3><strong>intégration au quotidien</strong></h3>\n<p>L&rsquo;un des avantages de la méditation en marchant est sa flexibilité. Elle peut être pratiquée à presque n&rsquo;importe quel moment de la journée et intégrée à vos routines habituelles. Faire de la méditation en marchant une partie de votre trajet quotidien vers le travail ou lors d&rsquo;une pause déjeuner peut être un moyen simple et efficace d&rsquo;introduire la pleine conscience dans votre vie de tous les jours.</p>\n<h3><strong>bienfaits pour la santé et le bien-Être</strong></h3>\n<p>Des études scientifiques ont démontré que la méditation en mouvement peut avoir des effets bénéfiques sur la santé, tant mentale que physique. Réduction du stress, amélioration de la concentration, renforcement du système immunitaire et amélioration de l&rsquo;humeur, les avantages sont multiples et bien documentés.</p>\n<p><strong>Renforcement de la Conscience Spatiale</strong> : En devenant plus conscients des environnements à travers lesquels nous passons, nous développons une meilleure conscience spatiale et une plus grande appréciation de notre entourage.</p>\n<p><strong>Cohérence Cardiaque</strong> : La méditation en marchant peut, grâce à la respiration rythmée, favoriser une meilleure cohérence cardiaque, ce qui est bénéfique pour la santé cardiovasculaire.</p>\n<p><strong>Détente Musculaire</strong> : Le mouvement peut aider à relâcher les tensions physiques, permettant une détente musculaire qui accompagne le calme mental.</p>\n<h3><strong>communauté et partage</strong></h3>\n<p>Pratiquer la méditation en marchant avec d&rsquo;autres personnes peut enrichir l&rsquo;expérience. Rejoindre un groupe ou simplement marcher avec un ami ou un membre de la famille peut créer un sentiment de connexion et d&rsquo;appartenance.</p>\n<p><strong>Échange d’Expériences</strong>: Partager vos sensations et expériences après la méditation en marchant peut ouvrir des perspectives nouvelles et renforcer la pratique collective.</p>\n<p>La méditation en marchant est une technique flexible et accessible, offrant un chemin vers la paix intérieure et la présence attentive. Que vous soyez un pratiquant expérimenté de la méditation ou un débutant, cette forme de méditation active peut vous apporter des bénéfices tangibles et améliorer votre qualité de vie.</p>\n<p>Tandis que nous explorons les paysages extérieurs, nous nous aventurons également dans les paysages intérieurs de notre propre conscience. La méditation en marchant est un art, qui, avec dévotion et pratique régulière, peut transformer notre rapport au monde et à nous-mêmes.</p>",
 "readingTime": 4,
 "faq": [],
 "regenerated": false
}